TkPlus/__init__.py
extended_tk/__init__.py
extended_tk-0.14.0.dist-info/LICENSE
extended_tk-0.14.0.dist-info/METADATA
extended_tk-0.14.0.dist-info/WHEEL
extended_tk-0.14.0.dist-info/top_level.txt
extended_tk-0.14.0.dist-info/RECORD
