Metadata-Version: 2.1
Name: extended-tk
Version: 0.14.0
Summary: An add-on for the tkinter package
Home-page: UNKNOWN
Author: Elidas
License: GNUGPLv3
Keywords: Tkinter
Platform: UNKNOWN
Classifier: Development Status :: 4 - Beta
Classifier: Intended Audience :: Developers
Classifier: Topic :: Utilities
Classifier: License :: OSI Approved :: GNU General Public License v3 (GPLv3)
Classifier: Operating System :: OS Independent
License-File: LICENSE
